{
    "title": "Cakes mascarpone sucrés et salés ",
    "private": false,
    "toppings": [
        {
            "quantity": "Cake sucré:",
            "unit": "",
            "name": ""
        },
        {
            "quantity": "250",
            "unit": "g",
            "name": "Mascarpone"
        },
        {
            "quantity": "4",
            "unit": "Œufs",
            "name": ""
        },
        {
            "quantity": "250",
            "unit": "g",
            "name": "Farine"
        },
        {
            "quantity": "1",
            "unit": "sachet",
            "name": "Levure chimique"
        },
        {
            "quantity": "1",
            "unit": "pincée",
            "name": "Sel"
        },
        {
            "quantity": "200",
            "unit": "g",
            "name": "Sucre en poudre"
        },
        {
            "quantity": "1",
            "unit": "c-à-s",
            "name": "Vanille liquide"
        },
        {
            "quantity": "Fruits",
            "unit": ": ",
            "name": "fruits rouges, poires, pommes, citron, …"
        },
        {
            "quantity": "Cake salé:",
            "unit": "",
            "name": ""
        },
        {
            "quantity": "250",
            "unit": "g",
            "name": "Mascarpone"
        },
        {
            "quantity": "4",
            "unit": "Œufs",
            "name": ""
        },
        {
            "quantity": "150",
            "unit": "g",
            "name": "Farine"
        },
        {
            "quantity": "1",
            "unit": "sachet",
            "name": "Levure chimique"
        },
        {
            "quantity": "1",
            "unit": "pincée",
            "name": "Sel"
        },
        {
            "quantity": "1",
            "unit": "pincée",
            "name": "Poivre"
        },
        {
            "quantity": "Garnitures :",
            "unit": "",
            "name": "tomates séchées, olives, melange de graines, jambon, saumon fumé, …"
        }
    ],
    "accessories": [
        {
            "name": "Plaque Aluminium perforée 40 x 30 cm",
            "picture": "https://boutique.guydemarle.com/2202-nq_social_share/plaque-aluminium-perforee-40-x-30-cm-guy-demarle.jpg",
            "url": ""
        },
        {
            "name": "Grand cul de poule 3,7L / 25 cm",
            "picture": "https://boutique.guydemarle.com/2234-nq_social_share/grand-cul-de-poule-37l-25-cm-guy-demarle.jpg",
            "url": ""
        },
        {
            "name": "Support cul-de-poule",
            "picture": "https://boutique.guydemarle.com/2231-nq_social_share/support-cul-de-poule-guy-demarle.jpg",
            "url": ""
        },
        {
            "name": "Fouet 13 cm",
            "picture": "https://boutique.guydemarle.com/5820-nq_social_share/fouet-13-cm-guy-demarle.jpg",
            "url": ""
        },
        {
            "name": "Petite spatule coudée 9 cm",
            "picture": "https://boutique.guydemarle.com/2142-nq_social_share/petite-spatule-coudee-9-cm-guy-demarle.jpg",
            "url": ""
        },
        {
            "name": "Mini Louche - Rose",
            "picture": "https://boutique.guydemarle.com/9092-nq_social_share/mini-louche-rose-cuisine.jpg",
            "url": ""
        },
        {
            "name": "Mélange 6 céréales pour pain - BIO - 500g",
            "picture": "https://boutique.guydemarle.com/11349-nq_social_share/melange-6-cereales-pour-pain-bio-500g.jpg",
            "url": ""
        },
        {
            "name": "Balance de cuisine en inox",
            "picture": "https://boutique.guydemarle.com/9078-nq_social_share/balance-de-cuisine-alimentaire-electronique-en-inox.jpg",
            "url": ""
        }
    ],
    "steps": [
        "Préchauffer votre four à 180 °C.",
        "Poser votre moule sur une plaque aluminium perforée.\n\n3 Cakes sucrés :\n\n",
        "Dans un cul de poule, fouetter le mascarpone, le sucre, les œufs et la vanille jusqu'à obtenir une pâte homogène.",
        "Ajouter le sel, la farine, la levure et mélanger.",
        "Répartir la pâte dans 3 cakes hauts à l’aide de la mini-louche.",
        "Pour éviter que les fruits ne tombent dans le fond du moule, saupoudrer un peu de farine dessus avant de les déposer dans les empreintes.",
        "Pour répartir les fruits une fois dans vos empreintes, utiliser la petite spatule coudée.\n\n3 Cakes salés :\n",
        "Dans un cul de poule, mélanger la mascarpone et les œufs.",
        "Ajouter la farine et la levure puis mélanger.",
        "Ajouter le gruyère, saler et poivrer.",
        "Répartir dans les 3 cakes hauts et ajouter les garnitures choisies.\nCuisson :",
        "Enfourner à 180°C pendant 40 min.",
        "Laisser refroidir avant de démouler."
    ],
    "for": "6",
    "preptime": "20",
    "resttime": "0",
    "cooktime": "40",
    "mold": {
        "name": "Moule 6 Cakes Hauts OHRA®",
        "picture": "https://boutique.guydemarle.com/11010-nq_social_share/moule-cake-haut.jpg",
        "url": "https://anneetsesdelices.fr/admin/recette/cakes-mascarpone-sucres-et-sales/#"
    }
}